pythonscriptoperations/__init__.py
pythonscriptoperations/operation_manager.py
pythonscriptoperations/test_operation_manager.py
pythonscriptoperations-0.1.1.dist-info/LICENSE
pythonscriptoperations-0.1.1.dist-info/METADATA
pythonscriptoperations-0.1.1.dist-info/WHEEL
pythonscriptoperations-0.1.1.dist-info/top_level.txt
pythonscriptoperations-0.1.1.dist-info/RECORD
