Metadata-Version: 2.1
Name: pythonscriptoperations
Version: 0.1.1
Summary: A package to manage and execute Python operations.
Home-page: https://github.com/NotCoffee418/PythonScriptOperations
Author: Stijn Raeymaekers
License: MIT
Keywords: python script operations manager console selection
Classifier: Development Status :: 3 - Alpha
Classifier: License :: OSI Approved :: MIT License
Classifier: Programming Language :: Python :: 3.6
Classifier: Programming Language :: Python :: 3.7
Classifier: Programming Language :: Python :: 3.8
Classifier: Programming Language :: Python :: 3.9
Classifier: Programming Language :: Python :: 3.10
Classifier: Programming Language :: Python :: 3.11
License-File: LICENSE
